{"nodes": [{"id": "f_dev_generative_bot_ai_aggregator_bot_handlers_language_py", "label": "language.py", "file_type": "code", "source_file": "bot/handlers/language.py", "source_location": "L1"}, {"id": "handlers_language_show_language_selection", "label": "show_language_selection()", "file_type": "code", "source_file": "bot/handlers/language.py", "source_location": "L17"}, {"id": "message", "label": "Message", "file_type": "code", "source_file": "bot/handlers/language.py", "source_location": "L17"}, {"id": "handlers_language_set_language", "label": "set_language()", "file_type": "code", "source_file": "bot/handlers/language.py", "source_location": "L22"}, {"id": "callbackquery", "label": "CallbackQuery", "file_type": "code", "source_file": "bot/handlers/language.py", "source_location": "L22"}, {"id": "handlers_language_choose_language", "label": "choose_language()", "file_type": "code", "source_file": "bot/handlers/language.py", "source_location": "L40"}], "edges": [{"source": "f_dev_generative_bot_ai_aggregator_bot_handlers_language_py", "target": "logging", "relation": "imports", "context": "import", "confidence": "EXTRACTED", "source_file": "bot/handlers/language.py", "source_location": "L1", "weight": 1.0}, {"source": "f_dev_generative_bot_ai_aggregator_bot_handlers_language_py", "target": "aiogram", "relation": "imports_from", "context": "import", "confidence": "EXTRACTED", "source_file": "bot/handlers/language.py", "source_location": "L3", "weight": 1.0}, {"source": "f_dev_generative_bot_ai_aggregator_bot_handlers_language_py", "target": "aiogram_types", "relation": "imports_from", "context": "import", "confidence": "EXTRACTED", "source_file": "bot/handlers/language.py", "source_location": "L4", "weight": 1.0}, {"source": "f_dev_generative_bot_ai_aggregator_bot_handlers_language_py", "target": "sqlalchemy", "relation": "imports_from", "context": "import", "confidence": "EXTRACTED", "source_file": "bot/handlers/language.py", "source_location": "L5", "weight": 1.0}, {"source": "f_dev_generative_bot_ai_aggregator_bot_handlers_language_py", "target": "backend_app_db_models", "relation": "imports_from", "context": "import", "confidence": "EXTRACTED", "source_file": "bot/handlers/language.py", "source_location": "L7", "weight": 1.0}, {"source": "f_dev_generative_bot_ai_aggregator_bot_handlers_language_py", "target": "backend_app_db_session", "relation": "imports_from", "context": "import", "confidence": "EXTRACTED", "source_file": "bot/handlers/language.py", "source_location": "L8", "weight": 1.0}, {"source": "f_dev_generative_bot_ai_aggregator_bot_handlers_language_py", "target": "bot_i18n", "relation": "imports_from", "context": "import", "confidence": "EXTRACTED", "source_file": "bot/handlers/language.py", "source_location": "L9", "weight": 1.0}, {"source": "f_dev_generative_bot_ai_aggregator_bot_handlers_language_py", "target": "bot_keyboards_language", "relation": "imports_from", "context": "import", "confidence": "EXTRACTED", "source_file": "bot/handlers/language.py", "source_location": "L10", "weight": 1.0}, {"source": "f_dev_generative_bot_ai_aggregator_bot_handlers_language_py", "target": "bot_services_start_message", "relation": "imports_from", "context": "import", "confidence": "EXTRACTED", "source_file": "bot/handlers/language.py", "source_location": "L11", "weight": 1.0}, {"source": "f_dev_generative_bot_ai_aggregator_bot_handlers_language_py", "target": "handlers_language_show_language_selection", "relation": "contains", "confidence": "EXTRACTED", "source_file": "bot/handlers/language.py", "source_location": "L17", "weight": 1.0}, {"source": "handlers_language_show_language_selection", "target": "message", "relation": "references", "context": "parameter_type", "confidence": "EXTRACTED", "source_file": "bot/handlers/language.py", "source_location": "L17", "weight": 1.0}, {"source": "f_dev_generative_bot_ai_aggregator_bot_handlers_language_py", "target": "handlers_language_set_language", "relation": "contains", "confidence": "EXTRACTED", "source_file": "bot/handlers/language.py", "source_location": "L22", "weight": 1.0}, {"source": "handlers_language_set_language", "target": "callbackquery", "relation": "references", "context": "parameter_type", "confidence": "EXTRACTED", "source_file": "bot/handlers/language.py", "source_location": "L22", "weight": 1.0}, {"source": "f_dev_generative_bot_ai_aggregator_bot_handlers_language_py", "target": "handlers_language_choose_language", "relation": "contains", "confidence": "EXTRACTED", "source_file": "bot/handlers/language.py", "source_location": "L40", "weight": 1.0}, {"source": "handlers_language_choose_language", "target": "message", "relation": "references", "context": "parameter_type", "confidence": "EXTRACTED", "source_file": "bot/handlers/language.py", "source_location": "L40", "weight": 1.0}, {"source": "handlers_language_choose_language", "target": "handlers_language_show_language_selection", "relation": "calls", "context": "call", "confidence": "EXTRACTED", "source_file": "bot/handlers/language.py", "source_location": "L41", "weight": 1.0}], "raw_calls": [{"caller_nid": "handlers_language_show_language_selection", "callee": "answer", "is_member_call": true, "source_file": "F:\\dev\\generative_bot\\ai_aggregator\\bot\\handlers\\language.py", "source_location": "L18"}, {"caller_nid": "handlers_language_show_language_selection", "callee": "t", "is_member_call": false, "source_file": "F:\\dev\\generative_bot\\ai_aggregator\\bot\\handlers\\language.py", "source_location": "L18"}, {"caller_nid": "handlers_language_show_language_selection", "callee": "language_keyboard", "is_member_call": false, "source_file": "F:\\dev\\generative_bot\\ai_aggregator\\bot\\handlers\\language.py", "source_location": "L18"}, {"caller_nid": "handlers_language_set_language", "callee": "split", "is_member_call": true, "source_file": "F:\\dev\\generative_bot\\ai_aggregator\\bot\\handlers\\language.py", "source_location": "L23"}, {"caller_nid": "handlers_language_set_language", "callee": "async_session", "is_member_call": false, "source_file": "F:\\dev\\generative_bot\\ai_aggregator\\bot\\handlers\\language.py", "source_location": "L24"}, {"caller_nid": "handlers_language_set_language", "callee": "scalar", "is_member_call": true, "source_file": "F:\\dev\\generative_bot\\ai_aggregator\\bot\\handlers\\language.py", "source_location": "L25"}, {"caller_nid": "handlers_language_set_language", "callee": "where", "is_member_call": true, "source_file": "F:\\dev\\generative_bot\\ai_aggregator\\bot\\handlers\\language.py", "source_location": "L25"}, {"caller_nid": "handlers_language_set_language", "callee": "select", "is_member_call": false, "source_file": "F:\\dev\\generative_bot\\ai_aggregator\\bot\\handlers\\language.py", "source_location": "L25"}, {"caller_nid": "handlers_language_set_language", "callee": "commit", "is_member_call": true, "source_file": "F:\\dev\\generative_bot\\ai_aggregator\\bot\\handlers\\language.py", "source_location": "L29"}, {"caller_nid": "handlers_language_set_language", "callee": "info", "is_member_call": true, "source_file": "F:\\dev\\generative_bot\\ai_aggregator\\bot\\handlers\\language.py", "source_location": "L30"}, {"caller_nid": "handlers_language_set_language", "callee": "answer", "is_member_call": true, "source_file": "F:\\dev\\generative_bot\\ai_aggregator\\bot\\handlers\\language.py", "source_location": "L31"}, {"caller_nid": "handlers_language_set_language", "callee": "t", "is_member_call": false, "source_file": "F:\\dev\\generative_bot\\ai_aggregator\\bot\\handlers\\language.py", "source_location": "L31"}, {"caller_nid": "handlers_language_set_language", "callee": "async_session", "is_member_call": false, "source_file": "F:\\dev\\generative_bot\\ai_aggregator\\bot\\handlers\\language.py", "source_location": "L33"}, {"caller_nid": "handlers_language_set_language", "callee": "scalar", "is_member_call": true, "source_file": "F:\\dev\\generative_bot\\ai_aggregator\\bot\\handlers\\language.py", "source_location": "L34"}, {"caller_nid": "handlers_language_set_language", "callee": "where", "is_member_call": true, "source_file": "F:\\dev\\generative_bot\\ai_aggregator\\bot\\handlers\\language.py", "source_location": "L34"}, {"caller_nid": "handlers_language_set_language", "callee": "select", "is_member_call": false, "source_file": "F:\\dev\\generative_bot\\ai_aggregator\\bot\\handlers\\language.py", "source_location": "L34"}, {"caller_nid": "handlers_language_set_language", "callee": "send_start_menu", "is_member_call": false, "source_file": "F:\\dev\\generative_bot\\ai_aggregator\\bot\\handlers\\language.py", "source_location": "L36"}]}